[
    {
        "name": "Real Madrid",
        "code": "RealMadrid",
        "web": "https://www.transfermarkt.com/real-madrid/startseite/verein/418"
    },
    {
        "name": "Barcelona",
        "code": "Barcelona",
        "web": "https://www.transfermarkt.com/fc-barcelona/startseite/verein/131"
    },
    {
        "name": "Inter Milan",
        "code": "InterMilan",
        "web": "https://www.transfermarkt.com/inter-mailand/startseite/verein/46"
    },
    {
        "name": "Manchester United",
        "code": "ManUtd",
        "web": "https://www.transfermarkt.com/manchester-united/startseite/verein/985"
    },
    {
        "name": "Milan",
        "code": "Milan",
        "web": "https://www.transfermarkt.com/ac-mailand/startseite/verein/5"
    },
    {
        "name": "Tottenham",
        "code": "Tottenham",
        "web": "https://www.transfermarkt.com/tottenham-hotspur/startseite/verein/148"
    },
    {
        "name": "Manchester City",
        "code": "ManCity",
        "web": "https://www.transfermarkt.com/manchester-city/startseite/verein/281"
    },
    {
        "name": "Bayern Munich",
        "code": "BayernMunich",
        "web": "https://www.transfermarkt.com/fc-bayern-munchen/startseite/verein/27"
    },
    {
        "name": "Arsenal",
        "code": "Arsenal",
        "web": "https://www.transfermarkt.com/fc-arsenal/startseite/verein/11"
    },
    {
        "name": "Galatasaray",
        "code": "Galatasaray",
        "web": "https://www.transfermarkt.com/galatasaray-istanbul/startseite/verein/141"
    },
    {
        "name": "PSG",
        "code": "PSG",
        "web": "https://www.transfermarkt.com/fc-paris-saint-germain/startseite/verein/583"
    },
    {
        "name": "Atletico Madrid",
        "code": "AtleticoMadrid",
        "web": "https://www.transfermarkt.com/atletico-madrid/startseite/verein/13"
    },
    {
        "name": "Napoli",
        "code": "Napoli",
        "web": "https://www.transfermarkt.com/ssc-neapel/startseite/verein/6195"
    },
    {
        "name": "Sevilla",
        "code": "Sevilla",
        "web": "https://www.transfermarkt.com/fc-sevilla/startseite/verein/368"
    },
    {
        "name": "Borussia Dortmund",
        "code": "Dortmund",
        "web": "https://www.transfermarkt.com/borussia-dortmund/startseite/verein/16"
    },
    {
        "name": "Copenhagen",
        "code": "Copenhagen",
        "web": "https://www.transfermarkt.com/fc-kopenhagen/startseite/verein/190"
    },
    {
        "name": "PSV Eindhoven",
        "code": "PSV",
        "web": "https://www.transfermarkt.com/psv-eindhoven/startseite/verein/383"
    },
    {
        "name": "Lens",
        "code": "Lens",
        "web": "https://www.transfermarkt.com/rc-lens/startseite/verein/826"
    },
    {
        "name": "Braga",
        "code": "Braga",
        "web": "https://www.transfermarkt.com/sc-braga/startseite/verein/1075"
    },
    {
        "name": "Union Berlin",
        "code": "UBerlin",
        "web": "https://www.transfermarkt.com/1-fc-union-berlin/startseite/verein/89"
    },
    {
        "name": "Real Sociedad",
        "code": "RealSociedad",
        "web": "https://www.transfermarkt.com/real-sociedad-san-sebastian/startseite/verein/681"
    },
    {
        "name": "Benfica",
        "code": "Benfica",
        "web": "https://www.transfermarkt.com/benfica-lissabon/startseite/verein/294"
    },
    {
        "name": "Salzburg",
        "code": "Salzburg",
        "web": "https://www.transfermarkt.com/red-bull-salzburg/startseite/verein/409"
    },
    {
        "name": "Lazio",
        "code": "Lazio",
        "web": "https://www.transfermarkt.com/lazio-rom/startseite/verein/398"
    },
    {
        "name": "Feyenoord",
        "code": "Feyenoord",
        "web": "https://www.transfermarkt.com/feyenoord-rotterdam/startseite/verein/234"
    },
    {
        "name": "Celtic",
        "code": "Celtic",
        "web": "https://www.transfermarkt.com/celtic-glasgow/startseite/verein/371"
    },
    {
        "name": "Newcastle",
        "code": "Newcastle",
        "web": "https://www.transfermarkt.com/newcastle-united/startseite/verein/762"
    },
    {
        "name": "Leipzig",
        "code": "Leipzig",
        "web": "https://www.transfermarkt.com/rasenballsport-leipzig/startseite/verein/23826"
    },
    {
        "name": "Young Boys",
        "code": "YoungBoys",
        "web": "https://www.transfermarkt.com/bsc-young-boys/startseite/verein/452"
    },
    {
        "name": "Red Star Belgrade",
        "code": "RedStarBelgrade",
        "web": "https://www.transfermarkt.com/roter-stern-belgrad/startseite/verein/159"
    },
    {
        "name": "Porto",
        "code": "Porto",
        "web": "https://www.transfermarkt.com/fc-porto/startseite/verein/720"
    },
    {
        "name": "Shakhtar Donetsk",
        "code": "ShakhtarDonetsk",
        "web": "https://www.transfermarkt.com/shakhtar-donetsk/startseite/verein/660"
    },
    {
        "name": "Antwerp",
        "code": "Antwerp",
        "web": "https://www.transfermarkt.com/royal-antwerpen-fc/startseite/verein/1096"
    }
]